README.md
setup.cfg
setup.py
bin/__init__.py
bin/probe.py
bin/store.py
cadena/__init__.py
cadena/abc.py
cadena.egg-info/PKG-INFO
cadena.egg-info/SOURCES.txt
cadena.egg-info/dependency_links.txt
cadena.egg-info/entry_points.txt
cadena.egg-info/not-zip-safe
cadena.egg-info/requires.txt
cadena.egg-info/top_level.txt
cadena/drivers/__init__.py
cadena/drivers/abc.py
cadena/drivers/common.py
cadena/drivers/alchemy/__init__.py
cadena/drivers/alchemy/db_objects.py
cadena/drivers/alchemy/driver.py
cadena/drivers/alchemy/helpers.py
cadena/drivers/memdict/__init__.py
cadena/drivers/mongo/__init__.py
cadena/fslike_dag/__init__.py
cadena/fslike_dag/links.py
cadena/fslike_dag/proto/__init__.py
cadena/fslike_dag/proto/dag_pb2.py