Metadata-Version: 1.1
Name: cadena
Version: 0.0.1.1546628370
Summary: Wierd and inefficient Tar clone.
Home-page: https://github.com/magniff/cadena
Author: magniff
Author-email: UNKNOWN
License: MIT license
Platform: unix
Platform: linux
Platform: osx
Platform: win32
Classifier: Programming Language :: Python :: 3.5
Classifier: Programming Language :: Python :: 3.6
Classifier: Programming Language :: Python :: 3.7
